app/__init__.py
app/normal_logs.py
app/suspicious_logs.py
app/utils.py
tests/__init__.py
tests/test_normal_logs.py
tests/test_suspicious_logs.py
tests/test_utils.py
log_crafter-1.0.1.dist-info/LICENSE
log_crafter-1.0.1.dist-info/METADATA
log_crafter-1.0.1.dist-info/WHEEL
log_crafter-1.0.1.dist-info/top_level.txt
log_crafter-1.0.1.dist-info/RECORD
