Metadata-Version: 2.1
Name: log-crafter
Version: 1.0.1
Summary: Une bibliothèque pour générer des logs
Home-page: https://github.com/votre_utilisateur/logcraft
Author: Teissier Léo
Author-email: leo.teissier@numericable.fr
Classifier: Programming Language :: Python :: 3
Classifier: License :: OSI Approved :: MIT License
Classifier: Operating System :: OS Independent
Requires-Python: >=3.6
License-File: LICENSE
Requires-Dist: pyyaml
Requires-Dist: setuptools
